phito_projen/__init__.py
phito_projen/python_package.py
phito_projen/components/__init__.py
phito_projen/components/commented_ini_file.py
phito_projen/components/lazy_sample_file.py
phito_projen/components/manifest_in.py
phito_projen/components/pyproject_toml.py
phito_projen/components/setup_py.py
phito_projen/components/templatized_file.py
phito_projen/components/commentable_files/__init__.py
phito_projen/components/commentable_files/ini_file.py
phito_projen/components/commentable_files/object_file.py
phito_projen/components/commentable_files/object_file_utils.py
phito_projen/components/pre_commit/__init__.py
phito_projen/components/projenrc_py/__init__.py
phito_projen/components/projenrc_py/projenrc_py.py
phito_projen/components/projenrc_py/templates/.projenrc.template.py.jinja
phito_projen/components/pylint/__init__.py
phito_projen/components/pylint/models.py
phito_projen/components/pylint/pylintrc.py
phito_projen/components/setup_cfg/__init__.py
phito_projen/components/setup_cfg/setup_cfg.py
phito_projen/components/setup_cfg/templates/setup.template.cfg.jinja
phito_projen/samples/__init__.py
phito_projen/samples/fastapi_app/__init__.py
phito_projen/samples/fastapi_app/sample.py
phitoduck_projen-0.1.1.dist-info/METADATA
phitoduck_projen-0.1.1.dist-info/WHEEL
phitoduck_projen-0.1.1.dist-info/top_level.txt
phitoduck_projen-0.1.1.dist-info/RECORD
